search_image_scraper/__init__.py
search_image_scraper/search_image_scraper.py
search_image_scraper-1.1.0.dist-info/LICENSE.txt
search_image_scraper-1.1.0.dist-info/METADATA
search_image_scraper-1.1.0.dist-info/WHEEL
search_image_scraper-1.1.0.dist-info/top_level.txt
search_image_scraper-1.1.0.dist-info/RECORD
