Metadata-Version: 2.2
Name: search_image_scraper
Version: 1.1.0
Summary: A package for downloading images from Google search.
Author-email: Yoad <botenyoad@gmail.com>
Project-URL: Homepage, https://github.com/GoatYoad/search_image_scraper
Project-URL: Repository, https://github.com/GoatYoad/search_image_scraper
Classifier: Programming Language :: Python :: 3
Classifier: License :: OSI Approved :: MIT License
Classifier: Operating System :: OS Independent
Requires-Python: >=3.8
License-File: LICENSE.txt
Requires-Dist: requests
Requires-Dist: selenium
Requires-Dist: beautifulsoup4
Requires-Dist: Pillow
Requires-Dist: imagehash
